commonroad_rl/__init__.py
commonroad_rl/evaluate_model.py
commonroad_rl/evaluate_model_sumo.py
commonroad_rl/generate_solution.py
commonroad_rl/plot_learning_curves.py
commonroad_rl/sensitivity_analysis.py
commonroad_rl/train_model.py
commonroad_rl/gym_commonroad/__init__.py
commonroad_rl/gym_commonroad/commonroad_env.py
commonroad_rl/gym_commonroad/configs.yaml
commonroad_rl/gym_commonroad/constants.py
commonroad_rl/gym_commonroad/action/__init__.py
commonroad_rl/gym_commonroad/action/action.py
commonroad_rl/gym_commonroad/action/vehicle.py
commonroad_rl/gym_commonroad/observation/__init__.py
commonroad_rl/gym_commonroad/observation/ego_observation.py
commonroad_rl/gym_commonroad/observation/goal_observation.py
commonroad_rl/gym_commonroad/observation/lanelet_network_observation.py
commonroad_rl/gym_commonroad/observation/observation.py
commonroad_rl/gym_commonroad/observation/observation_collector.py
commonroad_rl/gym_commonroad/observation/surrounding_observation.py
commonroad_rl/gym_commonroad/observation/traffic_sign_observation.py
commonroad_rl/gym_commonroad/reward/__init__.py
commonroad_rl/gym_commonroad/reward/dense_reward.py
commonroad_rl/gym_commonroad/reward/hybrid_reward.py
commonroad_rl/gym_commonroad/reward/reward.py
commonroad_rl/gym_commonroad/reward/reward_constructor.py
commonroad_rl/gym_commonroad/reward/sparse_reward.py
commonroad_rl/gym_commonroad/reward/termination.py
commonroad_rl/gym_commonroad/utils/__init__.py
commonroad_rl/gym_commonroad/utils/collision_type_checker.py
commonroad_rl/gym_commonroad/utils/conflict_zone.py
commonroad_rl/gym_commonroad/utils/navigator.py
commonroad_rl/gym_commonroad/utils/scenario.py
commonroad_rl/gym_commonroad/utils/scenario_io.py
commonroad_rl/tests/__init__.py
commonroad_rl/tests/conftest.py
commonroad_rl/tests/test_commonroad_rl.py
commonroad_rl/tests/gym_commonroad/__init__.py
commonroad_rl/tests/gym_commonroad/test_commonroad_env.py
commonroad_rl/tests/gym_commonroad/test_termination.py
commonroad_rl-2023.1.3.dist-info/LICENSE
commonroad_rl-2023.1.3.dist-info/METADATA
commonroad_rl-2023.1.3.dist-info/WHEEL
commonroad_rl-2023.1.3.dist-info/top_level.txt
commonroad_rl-2023.1.3.dist-info/RECORD
