Metadata-Version: 2.1
Name: commonroad-rl
Version: 2023.1.3
Summary: Tools for applying reinforcement learning on commonroad scenarios.
Home-page: https://commonroad.in.tum.de/
License: UNKNOWN
Keywords: autonomous,automated,vehicles,driving,motion,planning
Platform: UNKNOWN
Classifier: Intended Audience :: Developers
Classifier: Intended Audience :: Science/Research
Classifier: Programming Language :: Python
Classifier: Programming Language :: Python :: 3.7
Classifier: Operating System :: POSIX :: Linux
Requires-Dist: aenum (==3.1.11)
Requires-Dist: numpy
Requires-Dist: scipy
Requires-Dist: networkx
Requires-Dist: triangle
Requires-Dist: optuna
Requires-Dist: pytest
Requires-Dist: importlib-metadata (==4.13.0)
Requires-Dist: Polygon3 (==3.0.9.1)
Requires-Dist: pybind11 (==2.10.1)
Requires-Dist: tensorflow (==1.15.0)
Requires-Dist: shapely (==1.8.5)
Requires-Dist: setuptools (==50.3.2)
Requires-Dist: gym (==0.21.0)
Requires-Dist: stable-baselines
Requires-Dist: commonroad-io (==2022.3)
Requires-Dist: commonroad-vehicle-models (==3.0.2)
Requires-Dist: commonroad-drivability-checker (==2022.2.1)
Requires-Dist: commonroad-route-planner (==2022.3)
Requires-Dist: SALib (==1.3.13)
